MathSquare/__init__.py
MathSquare-0.0.7.dist-info/METADATA
MathSquare-0.0.7.dist-info/WHEEL
MathSquare-0.0.7.dist-info/top_level.txt
MathSquare-0.0.7.dist-info/RECORD
