Metadata-Version: 2.1
Name: MathSquare
Version: 0.0.7
Summary: A package for easy work with geometric formulas
Home-page: https://github.com/Zedikon/MathSquare/wiki/MathSquare-wiki
Author: Zedikon
Author-email: mrzedikon@gmail.com
License: UNKNOWN
Platform: UNKNOWN
Classifier: Programming Language :: Python :: 3.10
Classifier: License :: OSI Approved :: GNU General Public License v3 (GPLv3)
